README.rst
setup.py
gargant/__init__.py
gargant.dispatch.egg-info/PKG-INFO
gargant.dispatch.egg-info/SOURCES.txt
gargant.dispatch.egg-info/dependency_links.txt
gargant.dispatch.egg-info/namespace_packages.txt
gargant.dispatch.egg-info/top_level.txt
gargant/dispatch/__init__.py
gargant/dispatch/matching.py