Metadata-Version: 1.1
Name: gargant.dispatch
Version: 0.1
Summary: Flexible dispatcher for WSGI Applications
Home-page: https://github.com/hirokiky/gargant.dispatch
Author: hirokiky
Author-email: hirokiky@gmail.com
License: MIT
Platform: UNKNOWN
Classifier: Development Status :: 3 - Alpha
Classifier: License :: OSI Approved :: MIT License
Classifier: Environment :: Web Environment
Classifier: Programming Language :: Python :: 2.7
Classifier: Programming Language :: Python :: 3.3
Classifier: Topic :: Internet :: WWW/HTTP
Classifier: Topic :: Internet :: WWW/HTTP :: WSGI :: Application
